profound/__init__.py
profound/_base_client.py
profound/_client.py
profound/_compat.py
profound/_constants.py
profound/_exceptions.py
profound/_files.py
profound/_models.py
profound/_qs.py
profound/_resource.py
profound/_response.py
profound/_streaming.py
profound/_types.py
profound/_version.py
profound/py.typed
profound/_utils/__init__.py
profound/_utils/_compat.py
profound/_utils/_datetime_parse.py
profound/_utils/_json.py
profound/_utils/_logs.py
profound/_utils/_proxy.py
profound/_utils/_reflection.py
profound/_utils/_resources_proxy.py
profound/_utils/_streams.py
profound/_utils/_sync.py
profound/_utils/_transform.py
profound/_utils/_typing.py
profound/_utils/_utils.py
profound/lib/.keep
profound/resources/__init__.py
profound/resources/prompts.py
profound/resources/reports.py
profound/resources/content/__init__.py
profound/resources/content/content.py
profound/resources/content/optimization.py
profound/resources/logs/__init__.py
profound/resources/logs/logs.py
profound/resources/logs/raw.py
profound/resources/organizations/__init__.py
profound/resources/organizations/categories.py
profound/resources/organizations/organizations.py
profound/types/__init__.py
profound/types/organization_domains_response.py
profound/types/organization_get_personas_response.py
profound/types/organization_list_assets_response.py
profound/types/organization_models_response.py
profound/types/organization_regions_response.py
profound/types/prompt_answers_params.py
profound/types/prompt_answers_response.py
profound/types/report_citations_params.py
profound/types/report_citations_response.py
profound/types/report_get_bots_report_params.py
profound/types/report_get_referrals_report_params.py
profound/types/report_info.py
profound/types/report_response.py
profound/types/report_result.py
profound/types/report_sentiment_params.py
profound/types/report_visibility_params.py
profound/types/content/__init__.py
profound/types/content/optimization_list_params.py
profound-0.22.0.dist-info/METADATA
profound-0.22.0.dist-info/WHEEL
profound-0.22.0.dist-info/licenses/LICENSE
profound-0.22.0.dist-info/RECORD
